danya/__init__.py
daniil_baruah-0.4.1.dist-info/METADATA
daniil_baruah-0.4.1.dist-info/WHEEL
daniil_baruah-0.4.1.dist-info/top_level.txt
daniil_baruah-0.4.1.dist-info/RECORD
