Metadata-Version: 2.4
Name: daniil-baruah
Version: 0.4.1
Summary: My first module
Author: Daniil Baruah
Author-email: daniilbaruah76@gmail.com
Requires-Python: >=3.10
Dynamic: author
Dynamic: author-email
Dynamic: requires-python
Dynamic: summary
